xlrd2/__init__.py
xlrd2/biffh.py
xlrd2/book.py
xlrd2/compdoc.py
xlrd2/formatting.py
xlrd2/formula.py
xlrd2/info.py
xlrd2/sheet.py
xlrd2/timemachine.py
xlrd2/xldate.py
xlrd2/xlsx.py
xlrd2-1.3.4.data/scripts/runxlrd2.py
xlrd2-1.3.4.dist-info/LICENSE
xlrd2-1.3.4.dist-info/METADATA
xlrd2-1.3.4.dist-info/WHEEL
xlrd2-1.3.4.dist-info/top_level.txt
xlrd2-1.3.4.dist-info/RECORD
